subscript/defaults.py
subscript/external.py
subscript/macros.py
subscript/tabulatehdf5.py
subscript/util.py
subscript/wrappers.py
subscript/scripts/histograms.py
subscript/scripts/nfilters.py
subscript/scripts/nodes.py
subscript/scripts/spatial.py
subhaloscript-1.0.7.dist-info/METADATA
subhaloscript-1.0.7.dist-info/WHEEL
subhaloscript-1.0.7.dist-info/licenses/LICENSE
subhaloscript-1.0.7.dist-info/RECORD
